Design.v
`timescale 1ns / 1ps
//////////////////////////////////////////////////////////////////////////////////
// Company: 
// Engineer: 
// 
// Create Date: 13.04.2026 16:22:05
// Design Name: 
// Module Name: DtBCDencoder
// Project Name: 
// Target Devices: 
// Tool Versions: 
// Description: 
// 
// Dependencies: 
// 
// Revision:
// Revision 0.01 - File Created
// Additional Comments:
// 
//////////////////////////////////////////////////////////////////////////////////


module DtBCDencoder(
    input [9:0]a_i, 
    output reg [3:0]y_o
);

//10 input lines for 0-9
always@(*)
case (a_i)
10'b0000000001: y_o = 4'b0000; //0
10'b0000000010: y_o = 4'b0001; //1
10'b0000000100: y_o = 4'b0010; //2
10'b0000001000: y_o = 4'b0011; //3
10'b0000010000: y_o = 4'b0100; //4
10'b0000100000: y_o = 4'b0101; //5
10'b0001000000: y_o = 4'b0110; //6
10'b0010000000: y_o = 4'b0111; //7
10'b0100000000: y_o = 4'b1000; //8
10'b1000000000: y_o = 4'b1001; //9
default: y_o = 4'bxxxx; //X
endcase

endmodule

Testbench.v
`timescale 1ns / 1ps
//////////////////////////////////////////////////////////////////////////////////
// Company: 
// Engineer: 
// 
// Create Date: 13.04.2026 16:22:37
// Design Name: 
// Module Name: tb_DtBCDencoder
// Project Name: 
// Target Devices: 
// Tool Versions: 
// Description: 
// 
// Dependencies: 
// 
// Revision:
// Revision 0.01 - File Created
// Additional Comments:
// 
//////////////////////////////////////////////////////////////////////////////////


module tb_DtBCDencoder();
reg [9:0]a_i;
wire [3:0]y_o;

//instantiation
DtBCDencoder UUT(.a_i(a_i), 
    .y_o(y_o));

initial begin //feeding inputs
a_i = 10'b0000000000; //all 0s
#2 $display("Time: %0t | Decimal: None (%b) | BCD: %b", $time, a_i, y_o);
#3 a_i = 10'b0000000001; //0
#2 $display("Time: %0t | Decimal: 0 (%b) | BCD: %b", $time, a_i, y_o);
#3 a_i = 10'b0000000010; //1
#2 $display("Time: %0t | Decimal: 1 (%b) | BCD: %b", $time, a_i, y_o);
#3 a_i = 10'b0000000100; //2
#2 $display("Time: %0t | Decimal: 2 (%b) | BCD: %b", $time, a_i, y_o);
#3 a_i = 10'b0000001000; //3
#2 $display("Time: %0t | Decimal: 3 (%b) | BCD: %b", $time, a_i, y_o);
#3 a_i = 10'b0000010000; //4
#2 $display("Time: %0t | Decimal: 4 (%b) | BCD: %b", $time, a_i, y_o);
#3 a_i = 10'b0000100000; //5
#2 $display("Time: %0t | Decimal: 5 (%b) | BCD: %b", $time, a_i, y_o);
#3 a_i = 10'b0001000000; //6
#2 $display("Time: %0t | Decimal: 6 (%b) | BCD: %b", $time, a_i, y_o);
#3 a_i = 10'b0010000000; //7
#2 $display("Time: %0t | Decimal: 7 (%b) | BCD: %b", $time, a_i, y_o);
#3 a_i = 10'b0100000000; //8
#2 $display("Time: %0t | Decimal: 8 (%b) | BCD: %b", $time, a_i, y_o);
#3 a_i = 10'b1000000000; //9
#2 $display("Time: %0t | Decimal: 9 (%b) | BCD: %b", $time, a_i, y_o);
#3 $finish;
end

initial begin //capture
//$monitor("Time: %0t | Input lines: %b | BCD: %b", $time, a_i, y_o); //comment or remove all '$display()', then uncomment
$dumpfile("DtBCDencoder.vcd");
$dumpvars(0, tb_DtBCDencoder);
end

endmodule

DtBCDencoder.vcd
$date
   Wed Apr 15 12:17:00 2026
$end

$version
  2025.2
  $dumpfile ("DtBCDencoder.vcd") 
$end

$timescale
  1ps
$end

$scope module tb_DtBCDencoder $end
$var reg 10 ! a_i [9:0] $end
$var wire 4 " y_o [3:0] $end
$scope module UUT $end
$var wire 10 # a_i [9:0] $end
$var reg 4 $ y_o [3:0] $end
$upscope $end
$upscope $end
$enddefinitions $end

#0
$dumpvars
b0 !
bx "
b0 #
bx $
$end

#5000
b1 !
b0 "
b1 #
b0 $

#10000
b10 !
b1 "
b10 #
b1 $

#15000
b100 !
b10 "
b100 #
b10 $

#20000
b1000 !
b11 "
b1000 #
b11 $

#25000
b10000 !
b100 "
b10000 #
b100 $

#30000
b100000 !
b101 "
b100000 #
b101 $

#35000
b1000000 !
b110 "
b1000000 #
b110 $

#40000
b10000000 !
b111 "
b10000000 #
b111 $

#45000
b100000000 !
b1000 "
b100000000 #
b1000 $

#50000
b1000000000 !
b1001 "
b1000000000 #
b1001 $
